[
  {
    "data": {
      "id": "sros-02",
      "weight": "2",
      "name": "sros-02",
      "parent": "",
      "kind": "",
      "sourceEndpoint": "",
      "targetEndpoint": "",
      "endpoint": {
        "sourceEndpoint": "",
        "targetEndpoint": ""
      },
      "extraData": {
        "clabBinds": null,
        "clabImage": "registry.srlinux.dev/pub/vr-sros:22.7.R1",
        "clabKind": "vr-sros",
        "clabMgmtIPv4Address": "20.20.20.102",
        "clabName": "sros-02"
      }
    },
    "position": {
      "x": 0,
      "y": 0
    },
    "removed": false,
    "group": "nodes",
    "selected": false,
    "selectable": true,
    "locked": false,
    "grabbed": false,
    "grabbable": true,
    "classes": ""
  },
  {
    "data": {
      "id": "sros-04",
      "weight": "2",
      "name": "sros-04",
      "parent": "",
      "kind": "",
      "sourceEndpoint": "",
      "targetEndpoint": "",
      "endpoint": {
        "sourceEndpoint": "",
        "targetEndpoint": ""
      },
      "extraData": {
        "clabBinds": null,
        "clabImage": "registry.srlinux.dev/pub/vr-sros:22.7.R1",
        "clabKind": "vr-sros",
        "clabMgmtIPv4Address": "20.20.20.104",
        "clabName": "sros-04"
      }
    },
    "position": {
      "x": 0,
      "y": 0
    },
    "removed": false,
    "group": "nodes",
    "selected": false,
    "selectable": true,
    "locked": false,
    "grabbed": false,
    "grabbable": true,
    "classes": ""
  },
  {
    "data": {
      "id": "srl-01",
      "weight": "2",
      "name": "srl-01",
      "parent": "",
      "kind": "",
      "sourceEndpoint": "",
      "targetEndpoint": "",
      "endpoint": {
        "sourceEndpoint": "",
        "targetEndpoint": ""
      },
      "extraData": {
        "clabBinds": null,
        "clabImage": "ghcr.io/nokia/srlinux",
        "clabKind": "srl",
        "clabMgmtIPv4Address": "20.20.20.201",
        "clabName": "srl-01"
      }
    },
    "position": {
      "x": 0,
      "y": 0
    },
    "removed": false,
    "group": "nodes",
    "selected": false,
    "selectable": true,
    "locked": false,
    "grabbed": false,
    "grabbable": true,
    "classes": ""
  },
  {
    "data": {
      "id": "sros-01",
      "weight": "2",
      "name": "sros-01",
      "parent": "",
      "kind": "",
      "sourceEndpoint": "",
      "targetEndpoint": "",
      "endpoint": {
        "sourceEndpoint": "",
        "targetEndpoint": ""
      },
      "extraData": {
        "clabBinds": null,
        "clabImage": "registry.srlinux.dev/pub/vr-sros:22.7.R1",
        "clabKind": "vr-sros",
        "clabMgmtIPv4Address": "20.20.20.101",
        "clabName": "sros-01"
      }
    },
    "position": {
      "x": 0,
      "y": 0
    },
    "removed": false,
    "group": "nodes",
    "selected": false,
    "selectable": true,
    "locked": false,
    "grabbed": false,
    "grabbable": true,
    "classes": ""
  },
  {
    "data": {
      "id": "topoviewer",
      "weight": "2",
      "name": "topoviewer",
      "parent": "",
      "kind": "",
      "sourceEndpoint": "",
      "targetEndpoint": "",
      "endpoint": {
        "sourceEndpoint": "",
        "targetEndpoint": ""
      },
      "extraData": {
        "clabBinds": [
          "/home/suuser/clab/topo-file.yaml:/opt/local-bind/topo-file.yaml:rw"
        ],
        "clabImage": "ghcr.io/asadarafat/topoviewer:development",
        "clabKind": "linux",
        "clabMgmtIPv4Address": "20.20.20.21",
        "clabName": "topoviewer"
      }
    },
    "position": {
      "x": 0,
      "y": 0
    },
    "removed": false,
    "group": "nodes",
    "selected": false,
    "selectable": true,
    "locked": false,
    "grabbed": false,
    "grabbable": true,
    "classes": ""
  },
  {
    "data": {
      "id": "srl-02",
      "weight": "2",
      "name": "srl-02",
      "parent": "",
      "kind": "",
      "sourceEndpoint": "",
      "targetEndpoint": "",
      "endpoint": {
        "sourceEndpoint": "",
        "targetEndpoint": ""
      },
      "extraData": {
        "clabBinds": null,
        "clabImage": "ghcr.io/nokia/srlinux",
        "clabKind": "srl",
        "clabMgmtIPv4Address": "20.20.20.202",
        "clabName": "srl-02"
      }
    },
    "position": {
      "x": 0,
      "y": 0
    },
    "removed": false,
    "group": "nodes",
    "selected": false,
    "selectable": true,
    "locked": false,
    "grabbed": false,
    "grabbable": true,
    "classes": ""
  },
  {
    "data": {
      "id": "sros-03",
      "weight": "2",
      "name": "sros-03",
      "parent": "",
      "kind": "",
      "sourceEndpoint": "",
      "targetEndpoint": "",
      "endpoint": {
        "sourceEndpoint": "",
        "targetEndpoint": ""
      },
      "extraData": {
        "clabBinds": null,
        "clabImage": "registry.srlinux.dev/pub/vr-sros:22.7.R1",
        "clabKind": "vr-sros",
        "clabMgmtIPv4Address": "20.20.20.103",
        "clabName": "sros-03"
      }
    },
    "position": {
      "x": 0,
      "y": 0
    },
    "removed": false,
    "group": "nodes",
    "selected": false,
    "selectable": true,
    "locked": false,
    "grabbed": false,
    "grabbable": true,
    "classes": ""
  },
  {
    "data": {
      "id": "0",
      "source": "srl-01",
      "target": "sros-01",
      "weight": "1",
      "name": "srl-01::e1-1 \u003c--\u003e sros-01::eth1",
      "parent": "",
      "kind": "",
      "sourceEndpoint": "e1-1",
      "targetEndpoint": "eth1",
      "endpoint": {
        "sourceEndpoint": "e1-1",
        "targetEndpoint": "eth1"
      },
      "extraData": {
        "clabEndpoints": {
          "SourceEndpoint": "e1-1",
          "TargetEndpoint": "eth1"
        },
        "clabId": "0",
        "clabKind": "ClabLink",
        "clabName": "srl-01::e1-1 \u003c--\u003e sros-01::eth1",
        "clabServerUsername": "root",
        "clabSourceLongName": "clab-topoViewerDemo-srl-01",
        "clabTargetLongName": "clab-topoViewerDemo-sros-01"
      }
    },
    "position": {
      "x": 0,
      "y": 0
    },
    "removed": false,
    "group": "edges",
    "selected": false,
    "selectable": true,
    "locked": false,
    "grabbed": false,
    "grabbable": true,
    "classes": ""
  },
  {
    "data": {
      "id": "1",
      "source": "srl-01",
      "target": "sros-02",
      "weight": "1",
      "name": "srl-01::e1-2 \u003c--\u003e sros-02::eth1",
      "parent": "",
      "kind": "",
      "sourceEndpoint": "e1-2",
      "targetEndpoint": "eth1",
      "endpoint": {
        "sourceEndpoint": "e1-2",
        "targetEndpoint": "eth1"
      },
      "extraData": {
        "clabEndpoints": {
          "SourceEndpoint": "e1-2",
          "TargetEndpoint": "eth1"
        },
        "clabId": "1",
        "clabKind": "ClabLink",
        "clabName": "srl-01::e1-2 \u003c--\u003e sros-02::eth1",
        "clabServerUsername": "root",
        "clabSourceLongName": "clab-topoViewerDemo-srl-01",
        "clabTargetLongName": "clab-topoViewerDemo-sros-02"
      }
    },
    "position": {
      "x": 0,
      "y": 0
    },
    "removed": false,
    "group": "edges",
    "selected": false,
    "selectable": true,
    "locked": false,
    "grabbed": false,
    "grabbable": true,
    "classes": ""
  },
  {
    "data": {
      "id": "2",
      "source": "sros-01",
      "target": "sros-02",
      "weight": "1",
      "name": "sros-01::eth2 \u003c--\u003e sros-02::eth2",
      "parent": "",
      "kind": "",
      "sourceEndpoint": "eth2",
      "targetEndpoint": "eth2",
      "endpoint": {
        "sourceEndpoint": "eth2",
        "targetEndpoint": "eth2"
      },
      "extraData": {
        "clabEndpoints": {
          "SourceEndpoint": "eth2",
          "TargetEndpoint": "eth2"
        },
        "clabId": "2",
        "clabKind": "ClabLink",
        "clabName": "sros-01::eth2 \u003c--\u003e sros-02::eth2",
        "clabServerUsername": "root",
        "clabSourceLongName": "clab-topoViewerDemo-sros-01",
        "clabTargetLongName": "clab-topoViewerDemo-sros-02"
      }
    },
    "position": {
      "x": 0,
      "y": 0
    },
    "removed": false,
    "group": "edges",
    "selected": false,
    "selectable": true,
    "locked": false,
    "grabbed": false,
    "grabbable": true,
    "classes": ""
  },
  {
    "data": {
      "id": "3",
      "source": "sros-01",
      "target": "sros-03",
      "weight": "1",
      "name": "sros-01::eth3 \u003c--\u003e sros-03::eth3",
      "parent": "",
      "kind": "",
      "sourceEndpoint": "eth3",
      "targetEndpoint": "eth3",
      "endpoint": {
        "sourceEndpoint": "eth3",
        "targetEndpoint": "eth3"
      },
      "extraData": {
        "clabEndpoints": {
          "SourceEndpoint": "eth3",
          "TargetEndpoint": "eth3"
        },
        "clabId": "3",
        "clabKind": "ClabLink",
        "clabName": "sros-01::eth3 \u003c--\u003e sros-03::eth3",
        "clabServerUsername": "root",
        "clabSourceLongName": "clab-topoViewerDemo-sros-01",
        "clabTargetLongName": "clab-topoViewerDemo-sros-03"
      }
    },
    "position": {
      "x": 0,
      "y": 0
    },
    "removed": false,
    "group": "edges",
    "selected": false,
    "selectable": true,
    "locked": false,
    "grabbed": false,
    "grabbable": true,
    "classes": ""
  },
  {
    "data": {
      "id": "4",
      "source": "sros-02",
      "target": "sros-03",
      "weight": "1",
      "name": "sros-02::eth4 \u003c--\u003e sros-03::eth4",
      "parent": "",
      "kind": "",
      "sourceEndpoint": "eth4",
      "targetEndpoint": "eth4",
      "endpoint": {
        "sourceEndpoint": "eth4",
        "targetEndpoint": "eth4"
      },
      "extraData": {
        "clabEndpoints": {
          "SourceEndpoint": "eth4",
          "TargetEndpoint": "eth4"
        },
        "clabId": "4",
        "clabKind": "ClabLink",
        "clabName": "sros-02::eth4 \u003c--\u003e sros-03::eth4",
        "clabServerUsername": "root",
        "clabSourceLongName": "clab-topoViewerDemo-sros-02",
        "clabTargetLongName": "clab-topoViewerDemo-sros-03"
      }
    },
    "position": {
      "x": 0,
      "y": 0
    },
    "removed": false,
    "group": "edges",
    "selected": false,
    "selectable": true,
    "locked": false,
    "grabbed": false,
    "grabbable": true,
    "classes": ""
  },
  {
    "data": {
      "id": "5",
      "source": "sros-02",
      "target": "sros-04",
      "weight": "1",
      "name": "sros-02::eth5 \u003c--\u003e sros-04::eth5",
      "parent": "",
      "kind": "",
      "sourceEndpoint": "eth5",
      "targetEndpoint": "eth5",
      "endpoint": {
        "sourceEndpoint": "eth5",
        "targetEndpoint": "eth5"
      },
      "extraData": {
        "clabEndpoints": {
          "SourceEndpoint": "eth5",
          "TargetEndpoint": "eth5"
        },
        "clabId": "5",
        "clabKind": "ClabLink",
        "clabName": "sros-02::eth5 \u003c--\u003e sros-04::eth5",
        "clabServerUsername": "root",
        "clabSourceLongName": "clab-topoViewerDemo-sros-02",
        "clabTargetLongName": "clab-topoViewerDemo-sros-04"
      }
    },
    "position": {
      "x": 0,
      "y": 0
    },
    "removed": false,
    "group": "edges",
    "selected": false,
    "selectable": true,
    "locked": false,
    "grabbed": false,
    "grabbable": true,
    "classes": ""
  },
  {
    "data": {
      "id": "6",
      "source": "sros-03",
      "target": "sros-04",
      "weight": "1",
      "name": "sros-03::eth6 \u003c--\u003e sros-04::eth6",
      "parent": "",
      "kind": "",
      "sourceEndpoint": "eth6",
      "targetEndpoint": "eth6",
      "endpoint": {
        "sourceEndpoint": "eth6",
        "targetEndpoint": "eth6"
      },
      "extraData": {
        "clabEndpoints": {
          "SourceEndpoint": "eth6",
          "TargetEndpoint": "eth6"
        },
        "clabId": "6",
        "clabKind": "ClabLink",
        "clabName": "sros-03::eth6 \u003c--\u003e sros-04::eth6",
        "clabServerUsername": "root",
        "clabSourceLongName": "clab-topoViewerDemo-sros-03",
        "clabTargetLongName": "clab-topoViewerDemo-sros-04"
      }
    },
    "position": {
      "x": 0,
      "y": 0
    },
    "removed": false,
    "group": "edges",
    "selected": false,
    "selectable": true,
    "locked": false,
    "grabbed": false,
    "grabbable": true,
    "classes": ""
  },
  {
    "data": {
      "id": "7",
      "source": "sros-01",
      "target": "sros-04",
      "weight": "1",
      "name": "sros-01::eth4 \u003c--\u003e sros-04::eth4",
      "parent": "",
      "kind": "",
      "sourceEndpoint": "eth4",
      "targetEndpoint": "eth4",
      "endpoint": {
        "sourceEndpoint": "eth4",
        "targetEndpoint": "eth4"
      },
      "extraData": {
        "clabEndpoints": {
          "SourceEndpoint": "eth4",
          "TargetEndpoint": "eth4"
        },
        "clabId": "7",
        "clabKind": "ClabLink",
        "clabName": "sros-01::eth4 \u003c--\u003e sros-04::eth4",
        "clabServerUsername": "root",
        "clabSourceLongName": "clab-topoViewerDemo-sros-01",
        "clabTargetLongName": "clab-topoViewerDemo-sros-04"
      }
    },
    "position": {
      "x": 0,
      "y": 0
    },
    "removed": false,
    "group": "edges",
    "selected": false,
    "selectable": true,
    "locked": false,
    "grabbed": false,
    "grabbable": true,
    "classes": ""
  },
  {
    "data": {
      "id": "8",
      "source": "sros-03",
      "target": "srl-02",
      "weight": "1",
      "name": "sros-03::eth1 \u003c--\u003e srl-02::e1-3",
      "parent": "",
      "kind": "",
      "sourceEndpoint": "eth1",
      "targetEndpoint": "e1-3",
      "endpoint": {
        "sourceEndpoint": "eth1",
        "targetEndpoint": "e1-3"
      },
      "extraData": {
        "clabEndpoints": {
          "SourceEndpoint": "eth1",
          "TargetEndpoint": "e1-3"
        },
        "clabId": "8",
        "clabKind": "ClabLink",
        "clabName": "sros-03::eth1 \u003c--\u003e srl-02::e1-3",
        "clabServerUsername": "root",
        "clabSourceLongName": "clab-topoViewerDemo-sros-03",
        "clabTargetLongName": "clab-topoViewerDemo-srl-02"
      }
    },
    "position": {
      "x": 0,
      "y": 0
    },
    "removed": false,
    "group": "edges",
    "selected": false,
    "selectable": true,
    "locked": false,
    "grabbed": false,
    "grabbable": true,
    "classes": ""
  },
  {
    "data": {
      "id": "9",
      "source": "sros-04",
      "target": "srl-02",
      "weight": "1",
      "name": "sros-04::eth2 \u003c--\u003e srl-02::e1-4",
      "parent": "",
      "kind": "",
      "sourceEndpoint": "eth2",
      "targetEndpoint": "e1-4",
      "endpoint": {
        "sourceEndpoint": "eth2",
        "targetEndpoint": "e1-4"
      },
      "extraData": {
        "clabEndpoints": {
          "SourceEndpoint": "eth2",
          "TargetEndpoint": "e1-4"
        },
        "clabId": "9",
        "clabKind": "ClabLink",
        "clabName": "sros-04::eth2 \u003c--\u003e srl-02::e1-4",
        "clabServerUsername": "root",
        "clabSourceLongName": "clab-topoViewerDemo-sros-04",
        "clabTargetLongName": "clab-topoViewerDemo-srl-02"
      }
    },
    "position": {
      "x": 0,
      "y": 0
    },
    "removed": false,
    "group": "edges",
    "selected": false,
    "selectable": true,
    "locked": false,
    "grabbed": false,
    "grabbable": true,
    "classes": ""
  }
]